dataforge/schema/cdisc_odm.py
dataforge/sources/redcap/__init__.py
dataforge/sources/redcap/api.py
dataforge/sources/redcap/project.py
dataforge/sources/redcap/schema.py
dataforge-0.0.1.dist-info/LICENSE
dataforge-0.0.1.dist-info/METADATA
dataforge-0.0.1.dist-info/WHEEL
dataforge-0.0.1.dist-info/entry_points.txt
dataforge-0.0.1.dist-info/top_level.txt
dataforge-0.0.1.dist-info/RECORD
