Metadata-Version: 2.1
Name: dataforge
Version: 0.0.1
Summary: Tools for creating and packaging data products
Home-page: https://gitlab.com/phs-rcg/data-forge
Author: Phil Schumm
Author-email: pschumm@uchicago.edu
License: UNKNOWN
Platform: UNKNOWN
Requires-Dist: click (>=7.1.2)
Requires-Dist: pandas (>=1.0.4)
Requires-Dist: keyring (>=21.2.1)
Requires-Dist: xmarshal (>=0.0.1b1)
